MANIFEST.in
README.md
Readme.md
setup.py
magicsquare/__init__.py
magicsquare/magicsquare.py
magicsquare.egg-info/PKG-INFO
magicsquare.egg-info/SOURCES.txt
magicsquare.egg-info/dependency_links.txt
magicsquare.egg-info/top_level.txt