Metadata-Version: 1.0
Name: magicsquare
Version: 1.0.0
Summary: Magic Square allows you to generate magic square at any length in python
Home-page: https://github.com/JuneSunshine/Magic_Square
Author: JuneSunshine
Author-email: ljygeek@gmail.com
License: MIT Licence
Keywords: magicsquare python3 package
Platform: all
